/***************************************************************************************************
 * File:         $URL: http://obtuse.cs.jhu.edu/Projects/Library/Source/Branches/NASABot/Src/Lua/LuaLib/lopcodes.cpp $
 * Author:       $Author: OBTUSE\matthew $
 * Revision:     $Rev: 1168 $
 * Last Updated: $Date: 2007-09-29 11:47:34 -0400 (Sat, 29 Sep 2007) $
 * 
 * 
 * Copyright (c) 2004-2007, Matthew G Bolitho
 * All rights reserved.
 *
 *
 * Microsoft Reference License (Ms-RL)
 *   
 * This license governs use of the accompanying software. If you use the software, you accept 
 * this license. If you do not accept the license, do not use the software.
 *
 * 1. Definitions
 *  - The terms "reproduce," "reproduction" and "distribution" have the same meaning here as under 
 *    U.S. copyright law.
 *  - "You" means the licensee of the software.
 *  - "Your company" means the company you worked for when you downloaded the software.
 *  - "Reference use" means use of the software within your company as a reference, in read only 
 *    form, for the sole purposes of debugging your products, maintaining your products, or 
 *    enhancing the interoperability of your products with the software, and specifically excludes 
 *    the right to distribute the software outside of your company.
 *  - "Licensed patents" means any Licensor patent claims which read directly on the software as 
 *    distributed by the Licensor under this license.
 * 
 * 2. Grant of Rights
 *  (A) Copyright Grant- Subject to the terms of this license, the Licensor grants you a non-transferable, 
 *      non-exclusive, worldwide, royalty-free copyright license to reproduce the software for reference use.
 *  (B) Patent Grant- Subject to the terms of this license, the Licensor grants you a non-transferable,
 *      non-exclusive, worldwide, royalty-free patent license under licensed patents for reference use.
 * 
 * 3. Limitations
 *  (A) No Trademark License - This license does not grant you any rights to use the Licensor's name
 *      logo, or trademarks.
 *  (B) If you begin patent litigation against the Licensor over patents that you think may apply 
 *      to the software (including a cross-claim or counterclaim in a lawsuit), your license to the 
 *      software ends automatically.
 *  (C) The software is licensed "as-is." You bear the risk of using it. The Licensor gives no express 
 *      warranties, guarantees or conditions. You may have additional consumer rights under your local 
 *      laws which this license cannot change. To the extent permitted under your local laws, the 
 *      Licensor excludes the implied warranties of merchantability, fitness for a particular purpose 
 *      and non-infringement.
 *
 ***************************************************************************************************/





#define lopcodes_c
#define LUA_CORE


#include "lopcodes.h"


/* ORDER OP */

const char *const luaP_opnames[NUM_OPCODES+1] = {
  "MOVE",
  "LOADK",
  "LOADBOOL",
  "LOADNIL",
  "GETUPVAL",
  "GETGLOBAL",
  "GETTABLE",
  "SETGLOBAL",
  "SETUPVAL",
  "SETTABLE",
  "NEWTABLE",
  "SELF",
  "ADD",
  "SUB",
  "MUL",
  "DIV",
  "MOD",
  "POW",
  "UNM",
  "NOT",
  "LEN",
  "CONCAT",
  "JMP",
  "EQ",
  "LT",
  "LE",
  "TEST",
  "TESTSET",
  "CALL",
  "TAILCALL",
  "RETURN",
  "FORLOOP",
  "FORPREP",
  "TFORLOOP",
  "SETLIST",
  "CLOSE",
  "CLOSURE",
  "VARARG",
  NULL
};


#define opmode(t,a,b,c,m) (((t)<<7) | ((a)<<6) | ((b)<<4) | ((c)<<2) | (m))

const lu_byte luaP_opmodes[NUM_OPCODES] = {
/*       T  A    B       C     mode		   opcode	*/
  opmode(0, 1, OpArgR, OpArgN, iABC) 		/* OP_MOVE */
 ,opmode(0, 1, OpArgK, OpArgN, iABx)		/* OP_LOADK */
 ,opmode(0, 1, OpArgU, OpArgU, iABC)		/* OP_LOADBOOL */
 ,opmode(0, 1, OpArgR, OpArgN, iABC)		/* OP_LOADNIL */
 ,opmode(0, 1, OpArgU, OpArgN, iABC)		/* OP_GETUPVAL */
 ,opmode(0, 1, OpArgK, OpArgN, iABx)		/* OP_GETGLOBAL */
 ,opmode(0, 1, OpArgR, OpArgK, iABC)		/* OP_GETTABLE */
 ,opmode(0, 0, OpArgK, OpArgN, iABx)		/* OP_SETGLOBAL */
 ,opmode(0, 0, OpArgU, OpArgN, iABC)		/* OP_SETUPVAL */
 ,opmode(0, 0, OpArgK, OpArgK, iABC)		/* OP_SETTABLE */
 ,opmode(0, 1, OpArgU, OpArgU, iABC)		/* OP_NEWTABLE */
 ,opmode(0, 1, OpArgR, OpArgK, iABC)		/* OP_SELF */
 ,opmode(0, 1, OpArgK, OpArgK, iABC)		/* OP_ADD */
 ,opmode(0, 1, OpArgK, OpArgK, iABC)		/* OP_SUB */
 ,opmode(0, 1, OpArgK, OpArgK, iABC)		/* OP_MUL */
 ,opmode(0, 1, OpArgK, OpArgK, iABC)		/* OP_DIV */
 ,opmode(0, 1, OpArgK, OpArgK, iABC)		/* OP_MOD */
 ,opmode(0, 1, OpArgK, OpArgK, iABC)		/* OP_POW */
 ,opmode(0, 1, OpArgR, OpArgN, iABC)		/* OP_UNM */
 ,opmode(0, 1, OpArgR, OpArgN, iABC)		/* OP_NOT */
 ,opmode(0, 1, OpArgR, OpArgN, iABC)		/* OP_LEN */
 ,opmode(0, 1, OpArgR, OpArgR, iABC)		/* OP_CONCAT */
 ,opmode(0, 0, OpArgR, OpArgN, iAsBx)		/* OP_JMP */
 ,opmode(1, 0, OpArgK, OpArgK, iABC)		/* OP_EQ */
 ,opmode(1, 0, OpArgK, OpArgK, iABC)		/* OP_LT */
 ,opmode(1, 0, OpArgK, OpArgK, iABC)		/* OP_LE */
 ,opmode(1, 1, OpArgR, OpArgU, iABC)		/* OP_TEST */
 ,opmode(1, 1, OpArgR, OpArgU, iABC)		/* OP_TESTSET */
 ,opmode(0, 1, OpArgU, OpArgU, iABC)		/* OP_CALL */
 ,opmode(0, 1, OpArgU, OpArgU, iABC)		/* OP_TAILCALL */
 ,opmode(0, 0, OpArgU, OpArgN, iABC)		/* OP_RETURN */
 ,opmode(0, 1, OpArgR, OpArgN, iAsBx)		/* OP_FORLOOP */
 ,opmode(0, 1, OpArgR, OpArgN, iAsBx)		/* OP_FORPREP */
 ,opmode(1, 0, OpArgN, OpArgU, iABC)		/* OP_TFORLOOP */
 ,opmode(0, 0, OpArgU, OpArgU, iABC)		/* OP_SETLIST */
 ,opmode(0, 0, OpArgN, OpArgN, iABC)		/* OP_CLOSE */
 ,opmode(0, 1, OpArgU, OpArgN, iABx)		/* OP_CLOSURE */
 ,opmode(0, 1, OpArgU, OpArgN, iABC)		/* OP_VARARG */
};

